chronologger/__init__.py
chronologger/__version__.py
chronologger/model.py
chronologger/repository.py
chronologger/service.py
chronologger/timer.py
tests/__init__.py
tests/conftest.py
tests/context.py
tests/my_tests.py
tests/test_basic_chronologger.py
tests/test_model.py
tests/test_repository.py
tests/test_service.py
chronologger-0.0.0.dev23.dist-info/METADATA
chronologger-0.0.0.dev23.dist-info/WHEEL
chronologger-0.0.0.dev23.dist-info/entry_points.txt
chronologger-0.0.0.dev23.dist-info/top_level.txt
chronologger-0.0.0.dev23.dist-info/RECORD
