Metadata-Version: 2.1
Name: chronologger
Version: 0.0.0.dev23
Summary: Time utilities for Python code
Home-page: UNKNOWN
Author: Francisco Perez-Sorrosal
License: UNKNOWN
Keywords: time,utilities
Platform: UNKNOWN
Classifier: License :: OSI Approved :: BSD License
Classifier: Programming Language :: Python :: 3
Classifier: Programming Language :: Python :: 3.6
Classifier: Programming Language :: Python :: 3.7
Classifier: Programming Language :: Python :: 3.7
Requires-Dist: dataclasses ; python_version < "3.7"
Requires-Dist: typing-extensions ; python_version <= "3.7"
Provides-Extra: dev
Requires-Dist: bump2version ; extra == 'dev'
